swh/__init__.py
swh/loader/__init__.py
swh/loader/pypi/__init__.py
swh/loader/pypi/_version.py
swh/loader/pypi/client.py
swh/loader/pypi/converters.py
swh/loader/pypi/loader.py
swh/loader/pypi/tasks.py
swh/loader/pypi/tests/__init__.py
swh/loader/pypi/tests/common.py
swh/loader/pypi/tests/test_client.py
swh/loader/pypi/tests/test_converters.py
swh/loader/pypi/tests/test_loader.py
swh.loader.pypi-0.0.9.dist-info/AUTHORS
swh.loader.pypi-0.0.9.dist-info/LICENSE
swh.loader.pypi-0.0.9.dist-info/METADATA
swh.loader.pypi-0.0.9.dist-info/WHEEL
swh.loader.pypi-0.0.9.dist-info/top_level.txt
swh.loader.pypi-0.0.9.dist-info/RECORD
