Metadata-Version: 2.1
Name: swh.loader.pypi
Version: 0.0.9
Summary: Software Heritage PyPI Loader
Home-page: https://forge.softwareheritage.org/source/swh-loader-pypi
Author: Software Heritage developers
Author-email: swh-devel@inria.fr
License: UNKNOWN
Project-URL: Funding, https://www.softwareheritage.org/donate
Project-URL: Source, https://forge.softwareheritage.org/source/swh-loader-pypi
Project-URL: Bug Reports, https://forge.softwareheritage.org/maniphest
Platform: UNKNOWN
Classifier: Programming Language :: Python :: 3
Classifier: Intended Audience :: Developers
Classifier: License :: OSI Approved :: GNU General Public License v3 (GPLv3)
Classifier: Operating System :: OS Independent
Classifier: Development Status :: 5 - Production/Stable
Requires-Dist: setuptools
Requires-Dist: vcversioner
Requires-Dist: requests
Requires-Dist: arrow
Requires-Dist: pkginfo
Requires-Dist: swh.core
Requires-Dist: swh.model (>=0.0.28)
Requires-Dist: swh.storage (>=0.0.114)
Requires-Dist: swh.scheduler (>=0.0.39)
Requires-Dist: swh.loader.core (>=0.0.37)
Provides-Extra: testing
Requires-Dist: pytest ; extra == 'testing'
